.DS_Store
py_ball/__init__.py
py_ball/boxscore.py
py_ball/draft.py
py_ball/event.py
py_ball/image.py
py_ball/leaderboard.py
py_ball/league.py
py_ball/league_dash.py
py_ball/league_hustle.py
py_ball/playbyplay.py
py_ball/player.py
py_ball/salaries.py
py_ball/scoreboard.py
py_ball/synergy.py
py_ball/team.py
py_ball/utils.py
py_ball/vegas.py
py_ball/vegas_local.py
py_ball/winprobability.py
py_ball/wnba_salaries.py
py_ball/wnba_shots.py
py_ball/models/model.pickle
py_ball/tests/__init__.py
py_ball/tests/test_boxscore.py
py_ball/tests/test_draft.py
py_ball/tests/test_image.py
py_ball/tests/test_leaderboard.py
py_ball/tests/test_league.py
py_ball/tests/test_league_dash.py
py_ball/tests/test_playbyplay.py
py_ball/tests/test_player.py
py_ball/tests/test_scoreboard.py
py_ball/tests/test_team.py
py_ball-1.42.dist-info/LICENSE
py_ball-1.42.dist-info/METADATA
py_ball-1.42.dist-info/WHEEL
py_ball-1.42.dist-info/top_level.txt
py_ball-1.42.dist-info/RECORD
