Metadata-Version: 2.1
Name: py-ball
Version: 1.42
Summary: Python API wrapper for stats.nba.com with a focus on                  NBA and WNBA applications
Home-page: https://github.com/basketballrelativity/py_ball
Author: Patrick McFarlane & Avyay Varadarajan
Author-email: patmcfarla@gmail.com
License: UNKNOWN
Platform: UNKNOWN
Classifier: Programming Language :: Python :: 3
Classifier: License :: OSI Approved :: MIT License
Classifier: Operating System :: OS Independent
License-File: LICENSE
